meroxa/__init__.py
meroxa/applications.py
meroxa/client.py
meroxa/connectors.py
meroxa/constants.py
meroxa/functions.py
meroxa/pipelines.py
meroxa/resources.py
meroxa/types.py
meroxa/users.py
meroxa/utils.py
meroxa_py-1.3.2.dist-info/LICENSE.md
meroxa_py-1.3.2.dist-info/METADATA
meroxa_py-1.3.2.dist-info/WHEEL
meroxa_py-1.3.2.dist-info/top_level.txt
meroxa_py-1.3.2.dist-info/RECORD
