Metadata-Version: 2.1
Name: meroxa-py
Version: 1.3.2
Summary: Meroxa Platform API Python client
Home-page: https://meroxa.io/
Author: Eric Cheatham
Author-email: eric@meroxa.io
License: MIT
Project-URL: Source Code, https://github.com/meroxa/meroxa-py/
Project-URL: Issue Tracker, https://github.com/meroxa/meroxa-py/issues
Classifier: Programming Language :: Python
Classifier: License :: OSI Approved :: MIT License
Classifier: Operating System :: OS Independent
Requires-Python: >=3.9
License-File: LICENSE.md
Requires-Dist: aiohttp
